pyzpl/__init__.py
pyzpl-0.1.9.dist-info/DESCRIPTION.rst
pyzpl-0.1.9.dist-info/METADATA
pyzpl-0.1.9.dist-info/RECORD
pyzpl-0.1.9.dist-info/WHEEL
pyzpl-0.1.9.dist-info/entry_points.txt
pyzpl-0.1.9.dist-info/metadata.json
pyzpl-0.1.9.dist-info/top_level.txt
