Metadata-Version: 2.0
Name: pyzpl
Version: 0.1.9
Summary: ZPL: ZeroMQ Property Language
Home-page: https://github.com/mbarkhau/pyzpl/
Author: Manuel Barkhau
Author-email: mbarkhau@gmail.com
License: MIT
Keywords: zpl,zmq,serialization
Platform: UNKNOWN
Classifier: Development Status :: 4 - Beta
Classifier: Environment :: Console
Classifier: Intended Audience :: Developers
Classifier: License :: OSI Approved :: MIT License
Classifier: Operating System :: MacOS :: MacOS X
Classifier: Operating System :: POSIX
Classifier: Programming Language :: Python
Classifier: Programming Language :: Python :: 2
Classifier: Programming Language :: Python :: 3
Classifier: Topic :: Utilities
Provides-Extra: build
Requires-Dist: twine; extra == 'build'
Requires-Dist: wheel; extra == 'build'
Provides-Extra: dev
Requires-Dist: flake8; extra == 'dev'
Requires-Dist: pytest; extra == 'dev'
Requires-Dist: ipython; extra == 'dev'
Requires-Dist: pudb; extra == 'dev'
